djext/__init__.py
djext/apps.py
djext/blame/__init__.py
djext/blame/admin.py
djext/blame/forms/__init__.py
djext/blame/forms/forms.py
djext/blame/forms/models.py
djext/blame/models.py
djext/blame/views.py
djext/datetime/__init__.py
djext/datetime/forms/__init__.py
djext/datetime/forms/widgets.py
djext/http/__init__.py
djext/http/apps.py
djext/http/exceptions.py
djext/http/middleware.py
djext/http/wsgi.py
djext/json/__init__.py
djext/json/apps.py
djext/json/auth/__init__.py
djext/json/auth/decorators.py
djext/json/http/__init__.py
djext/json/http/response.py
djext/json/middleware.py
djext/json/views.py
djext/status/__init__.py
djext/status/apps.py
djext/status/urls.py
djext/status/views.py
djext/templates/base.html
djext/templatetags/__init__.py
djext/templatetags/generic.py
djext/templatetags/json.py
djext/templatetags/math.py
djext/templatetags/strings.py
djext/urls/__init__.py
djext/urls/converters.py
djext-0.5.2.dist-info/LICENSE
djext-0.5.2.dist-info/METADATA
djext-0.5.2.dist-info/WHEEL
djext-0.5.2.dist-info/RECORD
